{
    "name": "bugfix-jq-552",
    "version": "0.1.0",
    "description": "Attempt to detect and fix inconsistencies in jq's split/join behavior. See jq's issue #552.",
    "homepage": "https://github.com/joelpurra/jq-bugfix-jq-552",
    "bugs": "https://github.com/joelpurra/jq-bugfix-jq-552/issues",
    "author": {
        "name": "Joel Purra",
        "url": "http://joelpurra.com/"
    },
    "main": "./jq/main.jq",
    "repository": {
        "type": "git",
        "url": "git://github.com/joelpurra/jq-bugfix-jq-552.git"
    },
    "dependencies": {
        "joelpurra/jq-stress": "^0.1.2"
    },
    "engines": {
        "jq": "^1.5.0",
        "jqnpm": "^1.0.0"
    },
    "licenses": [{
        "type": "MIT",
        "url": "http://opensource.org/licenses/MIT"
    }],
    "keywords": [
        "jq-package"
    ]
}